mpesa/__init__.py
mpesa/client.py
mpesa/config.py
mpesa/exceptions.py
mpesa/utils.py
stripe/__init__.py
stripe/server.py
pesa_gateway-0.0.16.dist-info/LICENSE
pesa_gateway-0.0.16.dist-info/METADATA
pesa_gateway-0.0.16.dist-info/WHEEL
pesa_gateway-0.0.16.dist-info/RECORD
