Metadata-Version: 2.3
Name: pesa-gateway
Version: 0.0.16
Summary: A Python library for integrating with various payment gateways in Africa, with initial support for M-Pesa
License: MIT
Author: ThakaCreator
Requires-Python: >=3.10,<4.0
Classifier: License :: OSI Approved :: MIT License
Classifier: Programming Language :: Python :: 3
Classifier: Programming Language :: Python :: 3.10
Classifier: Programming Language :: Python :: 3.11
Classifier: Programming Language :: Python :: 3.12
Classifier: Programming Language :: Python :: 3.13
Requires-Dist: phonenumbers (>=9.0.0,<10.0.0)
Requires-Dist: python-dotenv (>=1.0.1,<2.0.0)
Requires-Dist: requests (>=2.32.3,<3.0.0)
Requires-Dist: stripe (>=12.1.0,<13.0.0)
